[
    {"Name" : "Prakesh", "Year" : 0, "Month" : 1, "Day" : 1, "isAnniversary" : false, "isBirthday" : true},
    {"Name" : "Saritha", "Year" : 0, "Month" : 1, "Day" : 25, "isAnniversary" : false, "isBirthday" : true},
    {"Name" : "Manya", "Year" : 0, "Month" : 1, "Day" : 31, "isAnniversary" : false, "isBirthday" : true},
    {"Name" : "Nidhi", "Year" : 0, "Month" : 2, "Day" : 1, "isAnniversary" : false, "isBirthday" : true},
    {"Name" : "Chandrakala", "Year" : 0, "Month" : 2, "Day" : 1, "isAnniversary" : false, "isBirthday" : true},
    {"Name" : "Sowbhagyamma", "Year" : 0, "Month" : 2, "Day" : 20, "isAnniversary" : false, "isBirthday" : true},
    {"Name" : "Sahana", "Year" : 0, "Month" : 2, "Day" : 24, "isAnniversary" : false, "isBirthday" : true},
    {"Name" : "Aanya", "Year" : 0, "Month" : 3, "Day" : 1, "isAnniversary" : false, "isBirthday" : true},
    {"Name" : "Anusha", "Year" : 1997, "Month" : 3, "Day" : 10, "isAnniversary" : false, "isBirthday" : true},
    {"Name" : "Savitha", "Year" : 0, "Month" : 3, "Day" : 14, "isAnniversary" : false, "isBirthday" : true},
    {"Name" : "Mallik", "Year" : 1959, "Month" : 4, "Day" : 5, "isAnniversary" : false, "isBirthday" : true},
    {"Name" : "Siri", "Year" : 0, "Month" : 4, "Day" : 15, "isAnniversary" : false, "isBirthday" : true},
    {"Name" : "Sharvana", "Year" : 0, "Month" : 4, "Day" : 18, "isAnniversary" : false, "isBirthday" : true},
    {"Name" : "Jeevika", "Year" : 2001, "Month" : 4, "Day" : 21, "isAnniversary" : false, "isBirthday" : true},
    {"Name" : "Shivu", "Year" : 0, "Month" : 4, "Day" : 30, "isAnniversary" : false, "isBirthday" : true},
    {"Name" : "Vishala", "Year" : 1972, "Month" : 5, "Day" : 5, "isAnniversary" : false, "isBirthday" : true},
    {"Name" : "Sherya", "Year" : 0, "Month" : 5, "Day" : 5, "isAnniversary" : false, "isBirthday" : true},
    {"Name" : "Anusha & Nithin", "Year" : 2020, "Month" : 5, "Day" : 13, "isAnniversary" : true, "isBirthday" : false},
    {"Name" : "Chandrakala & Sadhashivaiah", "Year" : 0, "Month" : 5, "Day" : 22, "isAnniversary" : true, "isBirthday" : false},
    {"Name" : "Sahana & Vishwanath", "Year" : 0, "Month" : 5, "Day" : 24, "isAnniversary" : true, "isBirthday" : false},
    {"Name" : "Annapurana & Prakesh", "Year" : 0, "Month" : 5, "Day" : 25, "isAnniversary" : true, "isBirthday" : false},
    {"Name" : "Sowbhagya & Guru", "Year" : 0, "Month" : 5, "Day" : 25, "isAnniversary" : true, "isBirthday" : false},
    {"Name" : "Pavithra M", "Year" : 0, "Month" : 6, "Day" : 3, "isAnniversary" : false, "isBirthday" : true},
    {"Name" : "Nata", "Year" : 0, "Month" : 6, "Day" : 5, "isAnniversary" : false, "isBirthday" : true},
    {"Name" : "Sadhashivaiah", "Year" : 0, "Month" : 6, "Day" : 10, "isAnniversary" : false, "isBirthday" : true},
    {"Name" : "Annapurana", "Year" : 0, "Month" : 6, "Day" : 12, "isAnniversary" : false, "isBirthday" : true},
    {"Name" : "Vishwanath", "Year" : 0, "Month" : 6, "Day" : 14, "isAnniversary" : false, "isBirthday" : true},
    {"Name" : "Mohana", "Year" : 0, "Month" : 6, "Day" : 19, "isAnniversary" : false, "isBirthday" : true},
    {"Name" : "Saritha & Shivu", "Year" : 0, "Month" : 6, "Day" : 18, "isAnniversary" : true, "isBirthday" : false},
    {"Name" : "Jeevan", "Year" : 2000, "Month" : 7, "Day" : 6, "isAnniversary" : false, "isBirthday" : true},
    {"Name" : "Guru", "Year" : 0, "Month" : 7, "Day" : 11, "isAnniversary" : false, "isBirthday" : true},
    {"Name" : "Manjula", "Year" : 0, "Month" : 8, "Day" : 22, "isAnniversary" : false, "isBirthday" : true},
    {"Name" : "Muruli", "Year" : 0, "Month" : 8, "Day" : 22, "isAnniversary" : false, "isBirthday" : true},
    {"Name" : "Mohana & Pavithra M", "Year" : 0, "Month" : 8, "Day" : 1, "isAnniversary" : true, "isBirthday" : false},
    {"Name" : "Nithin", "Year" : 0, "Month" : 9, "Day" : 14, "isAnniversary" : false, "isBirthday" : true},
    {"Name" : "Raju", "Year" : 0, "Month" : 9, "Day" : 24, "isAnniversary" : false, "isBirthday" : true},
    {"Name" : "Chethan", "Year" : 0, "Month" : 10, "Day" : 7, "isAnniversary" : false, "isBirthday" : true},
    {"Name" : "Deepak", "Year" : 1997, "Month" : 10, "Day" : 14, "isAnniversary" : false, "isBirthday" : true},
    {"Name" : "Chinthan", "Year" : 0, "Month" : 10, "Day" : 20, "isAnniversary" : false, "isBirthday" : true},
    {"Name" : "Shipla", "Year" : 0, "Month" : 11, "Day" : 12, "isAnniversary" : false, "isBirthday" : true},
    {"Name" : "Yoganand", "Year" : 0, "Month" : 11, "Day" : 19, "isAnniversary" : false, "isBirthday" : true},
    {"Name" : "Nata & Pavithra N", "Year" : 0, "Month" : 11, "Day" : 8, "isAnniversary" : true, "isBirthday" : false},
    {"Name" : "Pavithra N", "Year" : 0, "Month" : 12, "Day" : 2, "isAnniversary" : false, "isBirthday" : true}
  ]